shortfun/__init__.py
shortfun/shortfun.py
shortfun/underscore.py
shortfun-0.1.1.dist-info/WHEEL
shortfun-0.1.1.dist-info/METADATA
shortfun-0.1.1.dist-info/RECORD
