Metadata-Version: 2.1
Name: shortfun
Version: 0.1.1
Summary: Short lambda functions for functional built in operations
Home-page: https://www.github.com/alrudolph/shortfun
License: MIT
Author: Alex Rudolph
Author-email: alex3rudolph@gmail.com
Requires-Python: >=3.8,<4.0
Classifier: License :: OSI Approved :: MIT License
Classifier: Programming Language :: Python :: 3
Classifier: Programming Language :: Python :: 3.8
Classifier: Programming Language :: Python :: 3.9
Classifier: Programming Language :: Python :: 3.10
Requires-Dist: pytest (>=7.1.3,<8.0.0)
Project-URL: Repository, https://www.github.com/alrudolph/shortfun
